micro_pulse/__init__.py
micro_pulse/micro.py
micro_pulse-1.0.4.dist-info/LICENSE.txt
micro_pulse-1.0.4.dist-info/METADATA
micro_pulse-1.0.4.dist-info/WHEEL
micro_pulse-1.0.4.dist-info/top_level.txt
micro_pulse-1.0.4.dist-info/RECORD
