Metadata-Version: 2.1
Name: micro-pulse
Version: 1.0.4
Summary: Kafka Based Lightweight Python Microservice Framework
Home-page: https://gitlab.com/frog-network/micro-pulse
Author: Frog Dev
Author-email: dev@frog-mining.com
License: UNKNOWN
Download-URL: https://pypi.org/project/micro-pulse/
Keywords: kafka,python,microservice,framework
Platform: UNKNOWN
Classifier: Programming Language :: Python :: 3
Classifier: License :: OSI Approved :: MIT License
Classifier: Operating System :: OS Independent
Requires-Python: >=3.6
Requires-Dist: kafka-python (==2.0.0)
